terra_opp/__init__.py
terra_opp/admin.py
terra_opp/apps.py
terra_opp/filters.py
terra_opp/models.py
terra_opp/renderers.py
terra_opp/serializers.py
terra_opp/settings.py
terra_opp/signals.py
terra_opp/urls.py
terra_opp/views.py
terra_opp/migrations/0001_initial.py
terra_opp/migrations/0002_auto_20181123_1028.py
terra_opp/migrations/0003_auto_20190122_1551.py
terra_opp/migrations/0004_auto_20190711_1801.py
terra_opp/migrations/0005_remove_document.py
terra_opp/migrations/0006_picture_order_by.py
terra_opp/migrations/0007_auto_20190725_1600.py
terra_opp/migrations/__init__.py
terra_opp/tests/__init__.py
terra_opp/tests/factories.py
terra_opp/tests/mixins.py
terra_opp/tests/test_campaign.py
terra_opp/tests/test_viewpoints.py
test_opp/__init__.py
test_opp/settings.py
test_opp/urls.py
test_opp/wsgi.py
terra_opp-0.3.0.dist-info/METADATA
terra_opp-0.3.0.dist-info/WHEEL
terra_opp-0.3.0.dist-info/top_level.txt
terra_opp-0.3.0.dist-info/RECORD
