Metadata-Version: 2.1
Name: terra-opp
Version: 0.3.0
Summary: Observatoire Photographique des Paysages
Home-page: https://github.com/Terralego/terra-opp.git
Author: Makina Corpus
Author-email: terralego-pypi@makina-corpus.com
License: UNKNOWN
Platform: UNKNOWN
Classifier: Environment :: Web Environment
Classifier: Framework :: Django
Classifier: Intended Audience :: Developers
Classifier: Topic :: Internet :: WWW/HTTP
Classifier: Topic :: Internet :: WWW/HTTP :: Dynamic Content
Classifier: License :: OSI Approved :: MIT License
Classifier: Natural Language :: English
Classifier: Operating System :: OS Independent
Classifier: Programming Language :: Python
Classifier: Programming Language :: Python :: 3.6
Classifier: Programming Language :: Python :: 3.7
Requires-Dist: Django (==2.2.5)
Requires-Dist: deepmerge
Requires-Dist: django-terra-accounts (<0.4,>=0.3.3)
Requires-Dist: django-terra-utils (>=0.3.6)
Requires-Dist: drf-yasg (>=1.9)
Requires-Dist: mercantile (>=1.0)
Requires-Dist: packaging
Requires-Dist: psycopg2 (>=2.7)
Requires-Dist: requests (>=2.19)
Requires-Dist: terra-common (<0.4,>=0.3.1)
Provides-Extra: dev
Requires-Dist: coverage ; extra == 'dev'
Requires-Dist: factory-boy ; extra == 'dev'
Requires-Dist: flake8 ; extra == 'dev'
